ritmo/__init__.py
ritmo/__version__.py
ritmo/constants.py
ritmo/cycles.py
ritmo/main.py
ritmo/plots.py
ritmo/statistics.py
ritmo/utils.py
ritmo/edm/edm.py
ritmo/edm/figure.py
ritmo/edm/statistics.py
RITMO-1.6.1.dist-info/LICENSE
RITMO-1.6.1.dist-info/METADATA
RITMO-1.6.1.dist-info/WHEEL
RITMO-1.6.1.dist-info/top_level.txt
RITMO-1.6.1.dist-info/RECORD
