Metadata-Version: 2.1
Name: RITMO
Version: 1.6.1
Summary: Research Investigation of Timeseries with Multiday Oscillations
Home-page: https://github.com/rachel-stirling/RITMO
Author: Rachel E. Stirling
Author-email: rachelstirling1@gmail.com
Classifier: Programming Language :: Python :: 3
Classifier: License :: OSI Approved :: MIT License
Classifier: Operating System :: OS Independent
License-File: LICENSE
Requires-Dist: pandas (==1.3.5)
Requires-Dist: matplotlib (==3.5.3)
Requires-Dist: numpy (==1.21.6)
Requires-Dist: pyEDM (==1.14.0.0)
Requires-Dist: pymannkendall (==1.4.3)
Requires-Dist: pycwt (==0.3.0a22)
Requires-Dist: scikit-learn (==1.0.2)
Requires-Dist: scipy (==1.7.3)
